uniparser/__init__.py
uniparser/uniparser.py
uniprot_topology-0.1.dist-info/LICENSE
uniprot_topology-0.1.dist-info/METADATA
uniprot_topology-0.1.dist-info/WHEEL
uniprot_topology-0.1.dist-info/top_level.txt
uniprot_topology-0.1.dist-info/RECORD
