Metadata-Version: 2.1
Name: uniprot-topology
Version: 0.1
Summary: Simple parser for UniProt topological domains and other features
Home-page: https://github.com/noelgarber/uniparser
Author: Noel Garber
Author-email: ngarber93@gmail.com
Classifier: Programming Language :: Python :: 3
License-File: LICENSE
Requires-Dist: xmltodict
